devme/__init__.py
devme/cli.py
devme/core.py
devme/discovery.py
devme/export.py
devme/server.py
devme/services.yaml
devme-0.2.3.dist-info/METADATA
devme-0.2.3.dist-info/WHEEL
devme-0.2.3.dist-info/entry_points.txt
devme-0.2.3.dist-info/licenses/LICENSE
devme-0.2.3.dist-info/RECORD
