Metadata-Version: 2.4
Name: devme
Version: 0.2.3
Summary: Developer dashboard for project health and configuration status
Project-URL: Homepage, https://github.com/devme-project/devme
Project-URL: Documentation, https://github.com/devme-project/devme#readme
Project-URL: Repository, https://github.com/devme-project/devme
Project-URL: Issues, https://github.com/devme-project/devme/issues
Author-email: DevMe Contributors <devme@citizentools.ai>
License: MIT
License-File: LICENSE
Keywords: dashboard,developer,git,health,project,status
Classifier: Development Status :: 3 - Alpha
Classifier: Environment :: Console
Classifier: Environment :: Web Environment
Classifier: Intended Audience :: Developers
Classifier: License :: OSI Approved :: MIT License
Classifier: Programming Language :: Python :: 3
Classifier: Programming Language :: Python :: 3.8
Classifier: Programming Language :: Python :: 3.9
Classifier: Programming Language :: Python :: 3.10
Classifier: Programming Language :: Python :: 3.11
Classifier: Programming Language :: Python :: 3.12
Classifier: Topic :: Software Development :: Libraries :: Python Modules
Classifier: Topic :: Software Development :: Version Control :: Git
Classifier: Topic :: System :: Monitoring
Requires-Python: >=3.8
Requires-Dist: aiohttp>=3.8.0
Requires-Dist: click>=8.0.0
Requires-Dist: flask>=2.0.0
Requires-Dist: gitpython>=3.1.0
Requires-Dist: jinja2>=3.0.0
Requires-Dist: pyyaml>=6.0.0
Requires-Dist: requests>=2.25.0
